orchestraw/__init__.py
orchestraw/__main__.py
orchestraw/lyric.py
orchestraw/metaeditor.py
orchestraw-2.7.0.dist-info/METADATA
orchestraw-2.7.0.dist-info/WHEEL
orchestraw-2.7.0.dist-info/entry_points.txt
orchestraw-2.7.0.dist-info/licenses/LICENSE
orchestraw-2.7.0.dist-info/RECORD
