Metadata-Version: 2.4
Name: Orchestraw
Version: 2.7.0
Summary: Orchestraw which downloads NCM music with metadata and lyric
Project-URL: Homepage, https://github.com/crillerium/orchestraw
Project-URL: Issues, https://github.com/crillerium/orchestraw
Author-email: Crillerium <crillerium@outlook.com>
License-File: LICENSE
Classifier: License :: OSI Approved :: MIT License
Classifier: Operating System :: OS Independent
Classifier: Programming Language :: Python :: 3
Requires-Python: >=3.8
Requires-Dist: mutagen
Requires-Dist: requests
